Workbook

Sheet Planilha1
B5: Configurações
B6: Salário | D6: 5000
B7: Rendimento da carteira | D7: 0.01
B8: Sugestão de investimento | D8: =D6*30% -> 1500
B10: Investimento Mensal
B11: Qto devo investir? | D11: 500
A12: 2 | B12: Qto tempo? | D12: 5
A13: 5 | B13: Qual taxa mensal? | D13: 0.01079
A14: 10 | B14: Patrimônio? | D14: =FV(D13,D12*12,D11*-1) -> 41888.457
A15: 20 | B15: Dividendos Mensais? | D15: =D14*D7 -> 418.88457
A16: 30 | ARE16: Intervalos nomeados
B17: Cenários | C17: Patrimônio | D17: Dividendos | ARE17: Conservador, moderado, agressivo
B18: Qto em 2 anos? | C18: =FV($D$13,A12*12,$D$11*-1) -> 13613.814 | D18: =C18*$D$7 -> 136.13814
B19: Qto em 5 anos? | C19: =FV($D$13,A13*12,$D$11*-1) -> 41888.457 | D19: =C19*$D$7 -> 418.88457
B20: Qto em 10 anos? | C20: =FV($D$13,A14*12,$D$11*-1) -> 121642.11 | D20: =C20*$D$7 -> 1216.4211
B21: Qto em 20 anos? | C21: =FV($D$13,A15*12,$D$11*-1) -> 562599.2 | D21: =C21*$D$7 -> 5625.992
B22: Qto em 30 anos? | C22: =FV($D$13,A16*12,$D$11*-1) -> 2161084.8 | D22: =C22*$D$7 -> 21610.848
B24: Perfil | C24: Moderado
B25: Valor a ser investido por mês | D25: =D11 -> 500
ARE26: Chaves
B27: Tipos de FII | C27: % sugerido | D27: Valores
B28: Papel | C28: =VLOOKUP($C$24&"-"&B28,'Planilha-APOIO'!$A:$D,4,FALSE) -> 0.32 | D28: =$D$25*C28 -> 160
B29: Tijolo | C29: =VLOOKUP($C$24&"-"&B29,'Planilha-APOIO'!$A:$D,4,FALSE) -> 0.35 | D29: =$D$25*C29 -> 175
B30: Híbrido | C30: =VLOOKUP($C$24&"-"&B30,'Planilha-APOIO'!$A:$D,4,FALSE) -> 0.08 | D30: =$D$25*C30 -> 40
B31: FOFs | C31: =VLOOKUP($C$24&"-"&B31,'Planilha-APOIO'!$A:$D,4,FALSE) -> 0.05 | D31: =$D$25*C31 -> 25
B32: Desenvolvimento | C32: =VLOOKUP($C$24&"-"&B32,'Planilha-APOIO'!$A:$D,4,FALSE) -> 0.1 | D32: =$D$25*C32 -> 50
B33: Hotelaria | C33: =VLOOKUP($C$24&"-"&B33,'Planilha-APOIO'!$A:$D,4,FALSE) -> 0.1 | D33: =$D$25*C33 -> 50
D34: =SUM(D28:D33) -> 500

Sheet Planilha-APOIO
A2: Chave | B2: Perfil | C2: Tipos de FII | D2: % | G2: %
A3: =B3&"-"&C3 -> Conservador -Papel | B3: Conservador | C3: Papel | D3: 0.3 | F3: Moderado-Tijolo | G3: =VLOOKUP(F3,$A2:$D20,4,FALSE) -> 0.35
A4: =B4&"-"&C4 -> Conservador -Tijolo | B4: Conservador | C4: Tijolo | D4: 0.5
A5: =B5&"-"&C5 -> Conservador -Híbrido | B5: Conservador | C5: Híbrido | D5: 0.1
A6: =B6&"-"&C6 -> Conservador -FOFs | B6: Conservador | C6: FOFs | D6: 0.1
A7: =B7&"-"&C7 -> Conservador -Desenvolvimento | B7: Conservador | C7: Desenvolvimento | D7: 0
A8: =B8&"-"&C8 -> Conservador -Hotelaria | B8: Conservador | C8: Hotelaria | D8: 0
A9: =B9&"-"&C9 -> Moderado-Papel | B9: Moderado | C9: Papel | D9: 0.32
A10: =B10&"-"&C10 -> Moderado-Tijolo | B10: Moderado | C10: Tijolo | D10: 0.35
A11: =B11&"-"&C11 -> Moderado-Híbrido | B11: Moderado | C11: Híbrido | D11: 0.08
A12: =B12&"-"&C12 -> Moderado-FOFs | B12: Moderado | C12: FOFs | D12: 0.05
A13: =B13&"-"&C13 -> Moderado-Desenvolvimento | B13: Moderado | C13: Desenvolvimento | D13: 0.1
A14: =B14&"-"&C14 -> Moderado-Hotelaria | B14: Moderado | C14: Hotelaria | D14: 0.1
A15: =B15&"-"&C15 -> Agressivo-Papel | B15: Agressivo | C15: Papel | D15: 0.5
... A20: =B20&"-"&C20 -> Agressivo-Hotelaria | B20: Agressivo | C20: Hotelaria | D20: 0.1
